{
  "annotations": {
    "list": [
      {
        "builtIn": 1,
        "datasource": "RANCHER_MONITORING",
        "enable": true,
        "hide": true,
        "iconColor": "rgba(0, 211, 255, 1)",
        "name": "Annotations & Alerts",
        "type": "dashboard"
      }
    ]
  },
  "description": "oracledb dashboard",
  "editable": true,
  "gnetId": 3333,
  "graphTooltip": 1,
  "id": 9,
  "iteration": 1599465988278,
  "links": [],
  "panels": [
    {
      "collapsed": false,
      "datasource": "RANCHER_MONITORING",
      "gridPos": {
        "h": 1,
        "w": 24,
        "x": 0,
        "y": 0
      },
      "id": 319,
      "panels": [],
      "title": "Oracel overview",
      "type": "row"
    },
    {
      "cacheTimeout": null,
      "colorBackground": false,
      "colorValue": false,
      "colors": [
        "#299c46",
        "rgba(237, 129, 40, 0.89)",
        "#d44a3a"
      ],
      "datasource": "RANCHER_MONITORING",
      "decimals": null,
      "fieldConfig": {
        "defaults": {
          "custom": {}
        },
        "overrides": []
      },
      "format": "short",
      "gauge": {
        "maxValue": 100,
        "minValue": 0,
        "show": false,
        "thresholdLabels": false,
        "thresholdMarkers": true
      },
      "gridPos": {
        "h": 3,
        "w": 24,
        "x": 0,
        "y": 1
      },
      "id": 86,
      "interval": null,
      "links": [],
      "mappingType": 1,
      "mappingTypes": [
        {
          "name": "value to text",
          "value": 1
        },
        {
          "name": "range to text",
          "value": 2
        }
      ],
      "maxDataPoints": 100,
      "maxPerRow": 4,
      "nullPointMode": "connected",
      "nullText": null,
      "postfix": " days",
      "postfixFontSize": "50%",
      "prefix": "",
      "prefixFontSize": "50%",
      "rangeMaps": [
        {
          "from": "null",
          "text": "N/A",
          "to": "null"
        }
      ],
      "repeat": "dbinstance",
      "scopedVars": {
        "dbinstance": {
          "selected": false,
          "text": "ora19c",
          "value": "ora19c"
        }
      },
      "sparkline": {
        "fillColor": "rgba(31, 118, 189, 0.18)",
        "full": false,
        "lineColor": "rgb(31, 120, 193)",
        "show": false
      },
      "tableColumn": "",
      "targets": [
        {
          "expr": "avg(oracledb_uptime{dbinstance=~'$dbinstance'}) without (job)",
          "format": "time_series",
          "intervalFactor": 2,
          "refId": "A"
        }
      ],
      "thresholds": "",
      "title": "Uptime $dbinstance",
      "type": "singlestat",
      "valueFontSize": "80%",
      "valueMaps": [
        {
          "op": "=",
          "text": "N/A",
          "value": "null"
        }
      ],
      "valueName": "current"
    },
    {
      "cacheTimeout": null,
      "datasource": "RANCHER_MONITORING",
      "fieldConfig": {
        "defaults": {
          "custom": {},
          "mappings": [
            {
              "id": 0,
              "op": "=",
              "text": "DEAD",
              "type": 1,
              "value": "0"
            },
            {
              "id": 1,
              "op": "=",
              "text": "ALIVE",
              "type": 1,
              "value": "1"
            }
          ],
          "nullValueMode": "connected",
          "thresholds": {
            "mode": "absolute",
            "steps": [
              {
                "color": "rgba(245, 54, 54, 0.9)",
                "value": null
              },
              {
                "color": "rgba(237, 129, 40, 0.89)",
                "value": 0
              },
              {
                "color": "rgba(50, 172, 45, 0.97)",
                "value": 1
              }
            ]
          },
          "unit": "none"
        },
        "overrides": []
      },
      "gridPos": {
        "h": 4,
        "w": 6,
        "x": 0,
        "y": 4
      },
      "id": 313,
      "interval": "",
      "links": [],
      "maxDataPoints": 100,
      "options": {
        "colorMode": "value",
        "fieldOptions": {
          "calcs": [
            "lastNotNull"
          ],
          "defaults": {
            "mappings": [],
            "thresholds": {
              "mode": "absolute",
              "steps": [
                {
                  "color": "green",
                  "value": null
                },
                {
                  "color": "red",
                  "value": 80
                }
              ]
            }
          },
          "overrides": [],
          "values": false
        },
        "graphMode": "none",
        "justifyMode": "auto",
        "orientation": "horizontal",
        "reduceOptions": {
          "calcs": [
            "mean"
          ],
          "fields": "",
          "values": false
        }
      },
      "pluginVersion": "6.7.4",
      "targets": [
        {
          "calculatedInterval": "10m",
          "datasourceErrors": {},
          "errors": {},
          "expr": "oracledb_up{instance=\"$host\"}",
          "format": "time_series",
          "instant": false,
          "interval": "5m",
          "intervalFactor": 1,
          "legendFormat": "",
          "metric": "",
          "refId": "A",
          "step": 300
        }
      ],
      "title": "oracledb status",
      "type": "stat"
    },
    {
      "cacheTimeout": null,
      "datasource": "RANCHER_MONITORING",
      "fieldConfig": {
        "defaults": {
          "custom": {},
          "mappings": [],
          "nullValueMode": "connected",
          "thresholds": {
            "mode": "absolute",
            "steps": [
              {
                "color": "green",
                "value": null
              },
              {
                "color": "red",
                "value": 80
              }
            ]
          },
          "unit": "short"
        },
        "overrides": []
      },
      "gridPos": {
        "h": 4,
        "w": 6,
        "x": 6,
        "y": 4
      },
      "id": 315,
      "interval": "",
      "links": [],
      "maxDataPoints": 100,
      "options": {
        "colorMode": "value",
        "fieldOptions": {
          "calcs": [
            "lastNotNull"
          ],
          "defaults": {
            "mappings": [],
            "thresholds": {
              "mode": "absolute",
              "steps": [
                {
                  "color": "green",
                  "value": null
                },
                {
                  "color": "red",
                  "value": 80
                }
              ]
            }
          },
          "overrides": [],
          "values": false
        },
        "graphMode": "area",
        "justifyMode": "auto",
        "orientation": "horizontal",
        "reduceOptions": {
          "calcs": [
            "mean"
          ],
          "fields": "",
          "values": false
        }
      },
      "pluginVersion": "6.7.4",
      "targets": [
        {
          "calculatedInterval": "10m",
          "datasourceErrors": {},
          "errors": {},
          "expr": "oracledb_sessions_value{status=\"ACTIVE\",type=\"USER\"}",
          "format": "time_series",
          "interval": "",
          "intervalFactor": 1,
          "legendFormat": "",
          "metric": "",
          "refId": "A",
          "step": 60
        }
      ],
      "title": "active sessions",
      "type": "stat"
    },
    {
      "cacheTimeout": null,
      "datasource": "RANCHER_MONITORING",
      "fieldConfig": {
        "defaults": {
          "custom": {},
          "mappings": [],
          "nullValueMode": "connected",
          "thresholds": {
            "mode": "absolute",
            "steps": [
              {
                "color": "rgba(50, 172, 45, 0.97)",
                "value": null
              },
              {
                "color": "rgba(237, 129, 40, 0.89)",
                "value": 90
              },
              {
                "color": "rgba(245, 54, 54, 0.9)",
                "value": 95
              }
            ]
          },
          "unit": "none"
        },
        "overrides": []
      },
      "gridPos": {
        "h": 4,
        "w": 6,
        "x": 12,
        "y": 4
      },
      "id": 317,
      "interval": "",
      "links": [],
      "maxDataPoints": 100,
      "options": {
        "colorMode": "value",
        "fieldOptions": {
          "calcs": [
            "lastNotNull"
          ],
          "defaults": {
            "mappings": [],
            "thresholds": {
              "mode": "absolute",
              "steps": [
                {
                  "color": "green",
                  "value": null
                },
                {
                  "color": "red",
                  "value": 80
                }
              ]
            }
          },
          "overrides": [],
          "values": false
        },
        "graphMode": "area",
        "justifyMode": "auto",
        "orientation": "horizontal",
        "reduceOptions": {
          "calcs": [
            "mean"
          ],
          "fields": "",
          "values": false
        }
      },
      "pluginVersion": "6.7.4",
      "targets": [
        {
          "calculatedInterval": "10m",
          "datasourceErrors": {},
          "errors": {},
          "expr": "oracledb_activity_user_commits{instance=\"$host\"}",
          "format": "time_series",
          "interval": "5m",
          "intervalFactor": 1,
          "legendFormat": "",
          "metric": "",
          "refId": "A",
          "step": 300
        }
      ],
      "title": "user commits",
      "type": "stat"
    },
    {
      "cacheTimeout": null,
      "datasource": "RANCHER_MONITORING",
      "fieldConfig": {
        "defaults": {
          "custom": {},
          "mappings": [],
          "nullValueMode": "connected",
          "thresholds": {
            "mode": "absolute",
            "steps": [
              {
                "color": "green",
                "value": null
              },
              {
                "color": "red",
                "value": 80
              }
            ]
          },
          "unit": "none"
        },
        "overrides": []
      },
      "gridPos": {
        "h": 4,
        "w": 6,
        "x": 18,
        "y": 4
      },
      "id": 321,
      "interval": "",
      "links": [],
      "maxDataPoints": 100,
      "options": {
        "colorMode": "value",
        "fieldOptions": {
          "calcs": [
            "lastNotNull"
          ],
          "defaults": {
            "mappings": [],
            "thresholds": {
              "mode": "absolute",
              "steps": [
                {
                  "color": "green",
                  "value": null
                },
                {
                  "color": "red",
                  "value": 80
                }
              ]
            }
          },
          "overrides": [],
          "values": false
        },
        "graphMode": "area",
        "justifyMode": "auto",
        "orientation": "horizontal",
        "reduceOptions": {
          "calcs": [
            "mean"
          ],
          "fields": "",
          "values": false
        }
      },
      "pluginVersion": "6.7.4",
      "repeat": null,
      "targets": [
        {
          "calculatedInterval": "10m",
          "datasourceErrors": {},
          "errors": {},
          "expr": "oracledb_activity_execute_count{instance=\"$host\"}",
          "format": "time_series",
          "interval": "5m",
          "intervalFactor": 1,
          "legendFormat": "",
          "metric": "",
          "refId": "A",
          "step": 300
        }
      ],
      "title": "execute count",
      "type": "stat"
    },
    {
      "collapsed": true,
      "datasource": "RANCHER_MONITORING",
      "gridPos": {
        "h": 1,
        "w": 24,
        "x": 0,
        "y": 8
      },
      "id": 325,
      "panels": [
        {
          "aliasColors": {},
          "bars": false,
          "dashLength": 10,
          "dashes": false,
          "datasource": "RANCHER_MONITORING",
          "fieldConfig": {
            "defaults": {
              "custom": {}
            },
            "overrides": []
          },
          "fill": 1,
          "fillGradient": 0,
          "gridPos": {
            "h": 6,
            "w": 24,
            "x": 0,
            "y": 9
          },
          "hiddenSeries": false,
          "id": 61,
          "legend": {
            "alignAsTable": false,
            "avg": false,
            "current": false,
            "max": false,
            "min": false,
            "show": true,
            "total": false,
            "values": false
          },
          "lines": true,
          "linewidth": 1,
          "links": [],
          "maxPerRow": 4,
          "nullPointMode": "null",
          "options": {
            "dataLinks": []
          },
          "percentage": false,
          "pointradius": 5,
          "points": false,
          "renderer": "flot",
          "repeat": "dbinstance",
          "scopedVars": {
            "dbinstance": {
              "selected": false,
              "text": "ora19c",
              "value": "ora19c"
            }
          },
          "seriesOverrides": [],
          "spaceLength": 10,
          "stack": true,
          "steppedLine": false,
          "targets": [
            {
              "expr": "avg(oracledb_session{dbinstance=~\"$dbinstance\"}) without (job)",
              "format": "time_series",
              "hide": false,
              "interval": "",
              "intervalFactor": 1,
              "legendFormat": "{{state}} {{type}}",
              "refId": "A"
            }
          ],
          "thresholds": [],
          "timeFrom": null,
          "timeRegions": [],
          "timeShift": null,
          "title": "Sessions $dbinstance",
          "tooltip": {
            "shared": true,
            "sort": 0,
            "value_type": "individual"
          },
          "type": "graph",
          "xaxis": {
            "buckets": null,
            "mode": "time",
            "name": null,
            "show": true,
            "values": []
          },
          "yaxes": [
            {
              "format": "short",
              "label": null,
              "logBase": 1,
              "max": null,
              "min": null,
              "show": true
            },
            {
              "format": "short",
              "label": null,
              "logBase": 1,
              "max": null,
              "min": null,
              "show": false
            }
          ],
          "yaxis": {
            "align": false,
            "alignLevel": null
          }
        },
        {
          "aliasColors": {},
          "bars": false,
          "dashLength": 10,
          "dashes": false,
          "datasource": "RANCHER_MONITORING",
          "fieldConfig": {
            "defaults": {
              "custom": {}
            },
            "overrides": []
          },
          "fill": 1,
          "fillGradient": 0,
          "gridPos": {
            "h": 6,
            "w": 24,
            "x": 0,
            "y": 15
          },
          "hiddenSeries": false,
          "id": 57,
          "legend": {
            "alignAsTable": false,
            "avg": false,
            "current": false,
            "max": false,
            "min": false,
            "rightSide": false,
            "show": true,
            "total": false,
            "values": false
          },
          "lines": true,
          "linewidth": 2,
          "links": [],
          "maxPerRow": 4,
          "nullPointMode": "null",
          "options": {
            "dataLinks": []
          },
          "percentage": false,
          "pointradius": 5,
          "points": false,
          "renderer": "flot",
          "repeat": "dbinstance",
          "scopedVars": {
            "dbinstance": {
              "selected": false,
              "text": "ora19c",
              "value": "ora19c"
            }
          },
          "seriesOverrides": [],
          "spaceLength": 10,
          "stack": false,
          "steppedLine": false,
          "targets": [
            {
              "expr": "rate(oracledb_sysstat{dbinstance=~'$dbinstance',type=~'.*commit.*|.*rollback.*'}[10m])",
              "format": "time_series",
              "intervalFactor": 2,
              "legendFormat": "{{type}}",
              "refId": "A",
              "step": 10
            }
          ],
          "thresholds": [],
          "timeFrom": null,
          "timeRegions": [],
          "timeShift": null,
          "title": "User Commits / Rollbacks $dbinstance",
          "tooltip": {
            "shared": true,
            "sort": 0,
            "value_type": "individual"
          },
          "type": "graph",
          "xaxis": {
            "buckets": null,
            "mode": "time",
            "name": null,
            "show": true,
            "values": []
          },
          "yaxes": [
            {
              "format": "short",
              "label": null,
              "logBase": 1,
              "max": null,
              "min": null,
              "show": true
            },
            {
              "format": "short",
              "label": null,
              "logBase": 1,
              "max": null,
              "min": null,
              "show": true
            }
          ],
          "yaxis": {
            "align": false,
            "alignLevel": null
          }
        },
        {
          "aliasColors": {},
          "bars": false,
          "dashLength": 10,
          "dashes": false,
          "datasource": "RANCHER_MONITORING",
          "fieldConfig": {
            "defaults": {
              "custom": {}
            },
            "overrides": []
          },
          "fill": 1,
          "fillGradient": 0,
          "gridPos": {
            "h": 7,
            "w": 24,
            "x": 0,
            "y": 21
          },
          "hiddenSeries": false,
          "id": 246,
          "legend": {
            "avg": false,
            "current": false,
            "max": false,
            "min": false,
            "show": true,
            "total": false,
            "values": false
          },
          "lines": true,
          "linewidth": 1,
          "links": [],
          "maxPerRow": 4,
          "nullPointMode": "null",
          "options": {
            "dataLinks": []
          },
          "percentage": false,
          "pointradius": 5,
          "points": false,
          "renderer": "flot",
          "repeat": "dbinstance",
          "scopedVars": {
            "dbinstance": {
              "selected": false,
              "text": "ora19c",
              "value": "ora19c"
            }
          },
          "seriesOverrides": [],
          "spaceLength": 10,
          "stack": false,
          "steppedLine": false,
          "targets": [
            {
              "expr": "avg(oracledb_cachehitratio{dbinstance=~\"$dbinstance\",type!='cursor_cache_hit_ratio'}) without (job)",
              "format": "time_series",
              "intervalFactor": 2,
              "legendFormat": "{{type}}",
              "refId": "A"
            }
          ],
          "thresholds": [],
          "timeFrom": null,
          "timeRegions": [],
          "timeShift": null,
          "title": "Cache Hit Ratio $dbinstance",
          "tooltip": {
            "shared": true,
            "sort": 0,
            "value_type": "individual"
          },
          "type": "graph",
          "xaxis": {
            "buckets": null,
            "mode": "time",
            "name": null,
            "show": true,
            "values": []
          },
          "yaxes": [
            {
              "format": "percent",
              "label": "",
              "logBase": 1,
              "max": "100",
              "min": null,
              "show": true
            },
            {
              "format": "short",
              "label": null,
              "logBase": 1,
              "max": null,
              "min": null,
              "show": false
            }
          ],
          "yaxis": {
            "align": false,
            "alignLevel": null
          }
        },
        {
          "aliasColors": {},
          "bars": false,
          "dashLength": 10,
          "dashes": false,
          "datasource": "RANCHER_MONITORING",
          "fieldConfig": {
            "defaults": {
              "custom": {}
            },
            "overrides": []
          },
          "fill": 1,
          "fillGradient": 0,
          "gridPos": {
            "h": 8,
            "w": 24,
            "x": 0,
            "y": 28
          },
          "hiddenSeries": false,
          "id": 62,
          "legend": {
            "avg": false,
            "current": false,
            "max": false,
            "min": false,
            "show": true,
            "total": false,
            "values": false
          },
          "lines": true,
          "linewidth": 1,
          "links": [],
          "maxPerRow": 4,
          "nullPointMode": "null",
          "options": {
            "dataLinks": []
          },
          "percentage": false,
          "pointradius": 5,
          "points": false,
          "renderer": "flot",
          "repeat": "dbinstance",
          "scopedVars": {
            "dbinstance": {
              "selected": false,
              "text": "ora19c",
              "value": "ora19c"
            }
          },
          "seriesOverrides": [],
          "spaceLength": 10,
          "stack": false,
          "steppedLine": false,
          "targets": [
            {
              "expr": "rate(oracledb_sysstat{dbinstance=~'$dbinstance',type=~'.*count.*'}[10m])",
              "format": "time_series",
              "intervalFactor": 2,
              "legendFormat": "{{type}}",
              "refId": "A"
            }
          ],
          "thresholds": [],
          "timeFrom": null,
          "timeRegions": [],
          "timeShift": null,
          "title": "Executions / Parses $dbinstance",
          "tooltip": {
            "shared": true,
            "sort": 0,
            "value_type": "individual"
          },
          "type": "graph",
          "xaxis": {
            "buckets": null,
            "mode": "time",
            "name": null,
            "show": true,
            "values": []
          },
          "yaxes": [
            {
              "format": "short",
              "label": null,
              "logBase": 1,
              "max": null,
              "min": null,
              "show": true
            },
            {
              "format": "short",
              "label": null,
              "logBase": 1,
              "max": null,
              "min": null,
              "show": true
            }
          ],
          "yaxis": {
            "align": false,
            "alignLevel": null
          }
        },
        {
          "aliasColors": {},
          "bars": false,
          "dashLength": 10,
          "dashes": false,
          "datasource": "RANCHER_MONITORING",
          "fieldConfig": {
            "defaults": {
              "custom": {}
            },
            "overrides": []
          },
          "fill": 1,
          "fillGradient": 0,
          "gridPos": {
            "h": 7,
            "w": 24,
            "x": 0,
            "y": 36
          },
          "hiddenSeries": false,
          "id": 250,
          "legend": {
            "avg": false,
            "current": false,
            "max": false,
            "min": false,
            "show": false,
            "total": false,
            "values": false
          },
          "lines": true,
          "linewidth": 1,
          "links": [],
          "maxPerRow": 4,
          "nullPointMode": "null",
          "options": {
            "dataLinks": []
          },
          "percentage": false,
          "pointradius": 5,
          "points": false,
          "renderer": "flot",
          "repeat": "dbinstance",
          "scopedVars": {
            "dbinstance": {
              "selected": false,
              "text": "ora19c",
              "value": "ora19c"
            }
          },
          "seriesOverrides": [],
          "spaceLength": 10,
          "stack": false,
          "steppedLine": false,
          "targets": [
            {
              "expr": "avg(oracledb_cachehitratio{dbinstance=~\"$dbinstance\",type='cursor_cache_hit_ratio'}) without (job)",
              "format": "time_series",
              "intervalFactor": 2,
              "legendFormat": "{{type}}",
              "refId": "A"
            }
          ],
          "thresholds": [],
          "timeFrom": null,
          "timeRegions": [],
          "timeShift": null,
          "title": "Cursor Cache Hit Ratio $dbinstance",
          "tooltip": {
            "shared": true,
            "sort": 0,
            "value_type": "individual"
          },
          "type": "graph",
          "xaxis": {
            "buckets": null,
            "mode": "time",
            "name": null,
            "show": true,
            "values": []
          },
          "yaxes": [
            {
              "format": "short",
              "label": null,
              "logBase": 1,
              "max": null,
              "min": null,
              "show": true
            },
            {
              "format": "short",
              "label": null,
              "logBase": 1,
              "max": null,
              "min": null,
              "show": true
            }
          ],
          "yaxis": {
            "align": false,
            "alignLevel": null
          }
        }
      ],
      "title": "Oracle Sessions",
      "type": "row"
    },
    {
      "collapsed": true,
      "datasource": "RANCHER_MONITORING",
      "gridPos": {
        "h": 1,
        "w": 24,
        "x": 0,
        "y": 9
      },
      "id": 323,
      "panels": [
        {
          "aliasColors": {},
          "bars": false,
          "dashLength": 10,
          "dashes": false,
          "datasource": "RANCHER_MONITORING",
          "decimals": null,
          "editable": true,
          "error": false,
          "fieldConfig": {
            "defaults": {
              "custom": {}
            },
            "overrides": []
          },
          "fill": 2,
          "fillGradient": 0,
          "grid": {},
          "gridPos": {
            "h": 7,
            "w": 12,
            "x": 0,
            "y": 10
          },
          "hiddenSeries": false,
          "id": 327,
          "legend": {
            "alignAsTable": false,
            "avg": false,
            "current": false,
            "max": false,
            "min": false,
            "rightSide": false,
            "show": false,
            "total": false,
            "values": false
          },
          "lines": true,
          "linewidth": 2,
          "links": [],
          "nullPointMode": "null",
          "options": {
            "dataLinks": []
          },
          "percentage": false,
          "pointradius": 5,
          "points": false,
          "renderer": "flot",
          "seriesOverrides": [],
          "spaceLength": 10,
          "stack": false,
          "steppedLine": false,
          "targets": [
            {
              "calculatedInterval": "2m",
              "datasourceErrors": {},
              "errors": {},
              "expr": "oracledb_wait_time_concurrency{instance=\"$host\"}",
              "format": "time_series",
              "interval": "",
              "intervalFactor": 1,
              "legendFormat": "",
              "metric": "",
              "refId": "A",
              "step": 60
            }
          ],
          "thresholds": [],
          "timeFrom": null,
          "timeRegions": [],
          "timeShift": null,
          "title": "wait time concurrency",
          "tooltip": {
            "msResolution": false,
            "shared": true,
            "sort": 0,
            "value_type": "individual"
          },
          "type": "graph",
          "xaxis": {
            "buckets": null,
            "mode": "time",
            "name": null,
            "show": true,
            "values": []
          },
          "yaxes": [
            {
              "format": "short",
              "logBase": 1,
              "max": null,
              "min": 0,
              "show": true
            },
            {
              "format": "short",
              "logBase": 1,
              "max": null,
              "min": 0,
              "show": true
            }
          ],
          "yaxis": {
            "align": false,
            "alignLevel": null
          }
        },
        {
          "aliasColors": {},
          "bars": false,
          "dashLength": 10,
          "dashes": false,
          "datasource": "RANCHER_MONITORING",
          "decimals": null,
          "editable": true,
          "error": false,
          "fieldConfig": {
            "defaults": {
              "custom": {}
            },
            "overrides": []
          },
          "fill": 2,
          "fillGradient": 0,
          "grid": {},
          "gridPos": {
            "h": 7,
            "w": 12,
            "x": 12,
            "y": 10
          },
          "hiddenSeries": false,
          "id": 329,
          "legend": {
            "alignAsTable": false,
            "avg": false,
            "current": false,
            "max": false,
            "min": false,
            "rightSide": false,
            "show": false,
            "total": false,
            "values": false
          },
          "lines": true,
          "linewidth": 2,
          "links": [],
          "nullPointMode": "null",
          "options": {
            "dataLinks": []
          },
          "percentage": false,
          "pointradius": 5,
          "points": false,
          "renderer": "flot",
          "seriesOverrides": [],
          "spaceLength": 10,
          "stack": false,
          "steppedLine": false,
          "targets": [
            {
              "calculatedInterval": "2m",
              "datasourceErrors": {},
              "errors": {},
              "expr": "oracledb_wait_time_commit{instance=\"$host\"}",
              "format": "time_series",
              "interval": "",
              "intervalFactor": 1,
              "legendFormat": "",
              "metric": "",
              "refId": "A",
              "step": 60
            }
          ],
          "thresholds": [],
          "timeFrom": null,
          "timeRegions": [],
          "timeShift": null,
          "title": "wait time commit",
          "tooltip": {
            "msResolution": false,
            "shared": true,
            "sort": 0,
            "value_type": "individual"
          },
          "type": "graph",
          "xaxis": {
            "buckets": null,
            "mode": "time",
            "name": null,
            "show": true,
            "values": []
          },
          "yaxes": [
            {
              "format": "short",
              "logBase": 1,
              "max": null,
              "min": 0,
              "show": true
            },
            {
              "format": "short",
              "logBase": 1,
              "max": null,
              "min": 0,
              "show": true
            }
          ],
          "yaxis": {
            "align": false,
            "alignLevel": null
          }
        },
        {
          "aliasColors": {},
          "bars": false,
          "dashLength": 10,
          "dashes": false,
          "datasource": "RANCHER_MONITORING",
          "decimals": null,
          "editable": true,
          "error": false,
          "fieldConfig": {
            "defaults": {
              "custom": {}
            },
            "overrides": []
          },
          "fill": 2,
          "fillGradient": 0,
          "grid": {},
          "gridPos": {
            "h": 7,
            "w": 12,
            "x": 0,
            "y": 17
          },
          "hiddenSeries": false,
          "id": 331,
          "legend": {
            "alignAsTable": false,
            "avg": false,
            "current": false,
            "max": false,
            "min": false,
            "rightSide": false,
            "show": false,
            "total": false,
            "values": false
          },
          "lines": true,
          "linewidth": 2,
          "links": [],
          "nullPointMode": "null",
          "options": {
            "dataLinks": []
          },
          "percentage": false,
          "pointradius": 5,
          "points": false,
          "renderer": "flot",
          "seriesOverrides": [],
          "spaceLength": 10,
          "stack": false,
          "steppedLine": false,
          "targets": [
            {
              "calculatedInterval": "2m",
              "datasourceErrors": {},
              "errors": {},
              "expr": "oracledb_wait_time_system_io{instance=\"$host\"}",
              "format": "time_series",
              "interval": "",
              "intervalFactor": 1,
              "legendFormat": "",
              "metric": "",
              "refId": "A",
              "step": 60
            }
          ],
          "thresholds": [],
          "timeFrom": null,
          "timeRegions": [],
          "timeShift": null,
          "title": "wait time system io",
          "tooltip": {
            "msResolution": false,
            "shared": true,
            "sort": 0,
            "value_type": "individual"
          },
          "type": "graph",
          "xaxis": {
            "buckets": null,
            "mode": "time",
            "name": null,
            "show": true,
            "values": []
          },
          "yaxes": [
            {
              "format": "short",
              "logBase": 1,
              "max": null,
              "min": 0,
              "show": true
            },
            {
              "format": "short",
              "logBase": 1,
              "max": null,
              "min": 0,
              "show": true
            }
          ],
          "yaxis": {
            "align": false,
            "alignLevel": null
          }
        },
        {
          "aliasColors": {},
          "bars": false,
          "dashLength": 10,
          "dashes": false,
          "datasource": "RANCHER_MONITORING",
          "decimals": null,
          "editable": true,
          "error": false,
          "fieldConfig": {
            "defaults": {
              "custom": {}
            },
            "overrides": []
          },
          "fill": 2,
          "fillGradient": 0,
          "grid": {},
          "gridPos": {
            "h": 7,
            "w": 12,
            "x": 12,
            "y": 17
          },
          "hiddenSeries": false,
          "id": 333,
          "legend": {
            "alignAsTable": false,
            "avg": false,
            "current": false,
            "max": false,
            "min": false,
            "rightSide": false,
            "show": false,
            "total": false,
            "values": false
          },
          "lines": true,
          "linewidth": 2,
          "links": [],
          "nullPointMode": "null",
          "options": {
            "dataLinks": []
          },
          "percentage": false,
          "pointradius": 5,
          "points": false,
          "renderer": "flot",
          "seriesOverrides": [],
          "spaceLength": 10,
          "stack": false,
          "steppedLine": false,
          "targets": [
            {
              "calculatedInterval": "2m",
              "datasourceErrors": {},
              "errors": {},
              "expr": "oracledb_wait_time_user_io{instance=\"$host\"}\t",
              "format": "time_series",
              "interval": "",
              "intervalFactor": 1,
              "legendFormat": "",
              "metric": "",
              "refId": "A",
              "step": 60
            }
          ],
          "thresholds": [],
          "timeFrom": null,
          "timeRegions": [],
          "timeShift": null,
          "title": "wait time user io",
          "tooltip": {
            "msResolution": false,
            "shared": true,
            "sort": 0,
            "value_type": "individual"
          },
          "type": "graph",
          "xaxis": {
            "buckets": null,
            "mode": "time",
            "name": null,
            "show": true,
            "values": []
          },
          "yaxes": [
            {
              "format": "short",
              "logBase": 1,
              "max": null,
              "min": 0,
              "show": true
            },
            {
              "format": "short",
              "logBase": 1,
              "max": null,
              "min": 0,
              "show": true
            }
          ],
          "yaxis": {
            "align": false,
            "alignLevel": null
          }
        },
        {
          "aliasColors": {},
          "bars": false,
          "dashLength": 10,
          "dashes": false,
          "datasource": "RANCHER_MONITORING",
          "decimals": null,
          "editable": true,
          "error": false,
          "fieldConfig": {
            "defaults": {
              "custom": {}
            },
            "overrides": []
          },
          "fill": 2,
          "fillGradient": 0,
          "grid": {},
          "gridPos": {
            "h": 7,
            "w": 12,
            "x": 0,
            "y": 24
          },
          "hiddenSeries": false,
          "id": 335,
          "legend": {
            "alignAsTable": false,
            "avg": false,
            "current": false,
            "max": false,
            "min": false,
            "rightSide": false,
            "show": false,
            "total": false,
            "values": false
          },
          "lines": true,
          "linewidth": 2,
          "links": [],
          "nullPointMode": "null",
          "options": {
            "dataLinks": []
          },
          "percentage": false,
          "pointradius": 5,
          "points": false,
          "renderer": "flot",
          "seriesOverrides": [],
          "spaceLength": 10,
          "stack": false,
          "steppedLine": false,
          "targets": [
            {
              "calculatedInterval": "2m",
              "datasourceErrors": {},
              "errors": {},
              "expr": "oracledb_wait_time_application{instance=\"$host\"}\t",
              "format": "time_series",
              "interval": "",
              "intervalFactor": 1,
              "legendFormat": "",
              "metric": "",
              "refId": "A",
              "step": 60
            }
          ],
          "thresholds": [],
          "timeFrom": null,
          "timeRegions": [],
          "timeShift": null,
          "title": "wait time application",
          "tooltip": {
            "msResolution": false,
            "shared": true,
            "sort": 0,
            "value_type": "individual"
          },
          "type": "graph",
          "xaxis": {
            "buckets": null,
            "mode": "time",
            "name": null,
            "show": true,
            "values": []
          },
          "yaxes": [
            {
              "format": "short",
              "logBase": 1,
              "max": null,
              "min": 0,
              "show": true
            },
            {
              "format": "short",
              "logBase": 1,
              "max": null,
              "min": 0,
              "show": true
            }
          ],
          "yaxis": {
            "align": false,
            "alignLevel": null
          }
        },
        {
          "aliasColors": {},
          "bars": false,
          "dashLength": 10,
          "dashes": false,
          "datasource": "RANCHER_MONITORING",
          "decimals": null,
          "editable": true,
          "error": false,
          "fieldConfig": {
            "defaults": {
              "custom": {}
            },
            "overrides": []
          },
          "fill": 2,
          "fillGradient": 0,
          "grid": {},
          "gridPos": {
            "h": 7,
            "w": 12,
            "x": 12,
            "y": 24
          },
          "hiddenSeries": false,
          "id": 337,
          "legend": {
            "alignAsTable": false,
            "avg": false,
            "current": false,
            "max": false,
            "min": false,
            "rightSide": false,
            "show": false,
            "total": false,
            "values": false
          },
          "lines": true,
          "linewidth": 2,
          "links": [],
          "nullPointMode": "null",
          "options": {
            "dataLinks": []
          },
          "percentage": false,
          "pointradius": 5,
          "points": false,
          "renderer": "flot",
          "seriesOverrides": [],
          "spaceLength": 10,
          "stack": false,
          "steppedLine": false,
          "targets": [
            {
              "calculatedInterval": "2m",
              "datasourceErrors": {},
              "errors": {},
              "expr": "oracledb_wait_time_network{instance=\"$host\"}\t",
              "format": "time_series",
              "interval": "",
              "intervalFactor": 1,
              "legendFormat": "",
              "metric": "",
              "refId": "A",
              "step": 60
            }
          ],
          "thresholds": [],
          "timeFrom": null,
          "timeRegions": [],
          "timeShift": null,
          "title": "wait time network",
          "tooltip": {
            "msResolution": false,
            "shared": true,
            "sort": 0,
            "value_type": "individual"
          },
          "type": "graph",
          "xaxis": {
            "buckets": null,
            "mode": "time",
            "name": null,
            "show": true,
            "values": []
          },
          "yaxes": [
            {
              "format": "short",
              "logBase": 1,
              "max": null,
              "min": 0,
              "show": true
            },
            {
              "format": "short",
              "logBase": 1,
              "max": null,
              "min": 0,
              "show": true
            }
          ],
          "yaxis": {
            "align": false,
            "alignLevel": null
          }
        }
      ],
      "title": "Oracle Locks",
      "type": "row"
    },
    {
      "collapsed": true,
      "datasource": "RANCHER_MONITORING",
      "gridPos": {
        "h": 1,
        "w": 24,
        "x": 0,
        "y": 10
      },
      "id": 279,
      "panels": [
        {
          "cacheTimeout": null,
          "colorBackground": false,
          "colorValue": false,
          "colors": [
            "#299c46",
            "rgba(237, 129, 40, 0.89)",
            "#d44a3a"
          ],
          "datasource": "RANCHER_MONITORING",
          "decimals": null,
          "fieldConfig": {
            "defaults": {
              "custom": {}
            },
            "overrides": []
          },
          "format": "percent",
          "gauge": {
            "maxValue": 100,
            "minValue": 0,
            "show": true,
            "thresholdLabels": true,
            "thresholdMarkers": true
          },
          "gridPos": {
            "h": 7,
            "w": 8,
            "x": 0,
            "y": 66
          },
          "id": 232,
          "interval": null,
          "links": [],
          "mappingType": 1,
          "mappingTypes": [
            {
              "name": "value to text",
              "value": 1
            },
            {
              "name": "range to text",
              "value": 2
            }
          ],
          "maxDataPoints": 100,
          "nullPointMode": "connected",
          "nullText": null,
          "postfix": "",
          "postfixFontSize": "50%",
          "prefix": "",
          "prefixFontSize": "50%",
          "rangeMaps": [
            {
              "from": "null",
              "text": "N/A",
              "to": "null"
            }
          ],
          "sparkline": {
            "fillColor": "rgba(31, 118, 189, 0.18)",
            "full": false,
            "lineColor": "rgb(31, 120, 193)",
            "show": false
          },
          "tableColumn": "",
          "targets": [
            {
              "expr": "avg(oracledb_recovery{database='$database',type=\"percent_space_used\"})",
              "format": "time_series",
              "hide": false,
              "intervalFactor": 2,
              "legendFormat": "",
              "refId": "A"
            }
          ],
          "thresholds": "50,85",
          "title": "FRA Used",
          "type": "singlestat",
          "valueFontSize": "70%",
          "valueMaps": [
            {
              "op": "=",
              "text": "N/A",
              "value": "null"
            }
          ],
          "valueName": "max"
        },
        {
          "cacheTimeout": null,
          "colorBackground": false,
          "colorValue": false,
          "colors": [
            "#299c46",
            "rgba(237, 129, 40, 0.89)",
            "#d44a3a"
          ],
          "datasource": "RANCHER_MONITORING",
          "decimals": null,
          "fieldConfig": {
            "defaults": {
              "custom": {}
            },
            "overrides": []
          },
          "format": "percent",
          "gauge": {
            "maxValue": 100,
            "minValue": 0,
            "show": true,
            "thresholdLabels": true,
            "thresholdMarkers": true
          },
          "gridPos": {
            "h": 7,
            "w": 8,
            "x": 8,
            "y": 66
          },
          "id": 254,
          "interval": null,
          "links": [],
          "mappingType": 1,
          "mappingTypes": [
            {
              "name": "value to text",
              "value": 1
            },
            {
              "name": "range to text",
              "value": 2
            }
          ],
          "maxDataPoints": 100,
          "nullPointMode": "connected",
          "nullText": null,
          "postfix": "",
          "postfixFontSize": "50%",
          "prefix": "",
          "prefixFontSize": "50%",
          "rangeMaps": [
            {
              "from": "null",
              "text": "N/A",
              "to": "null"
            }
          ],
          "sparkline": {
            "fillColor": "rgba(31, 118, 189, 0.18)",
            "full": false,
            "lineColor": "rgb(31, 120, 193)",
            "show": false
          },
          "tableColumn": "",
          "targets": [
            {
              "expr": "avg(oracledb_recovery{database='$database',type=\"percent_space_reclaimable\"})",
              "format": "time_series",
              "intervalFactor": 2,
              "refId": "A"
            }
          ],
          "thresholds": "50,80",
          "title": "FRA Reclaimable",
          "type": "singlestat",
          "valueFontSize": "70%",
          "valueMaps": [
            {
              "op": "=",
              "text": "N/A",
              "value": "null"
            }
          ],
          "valueName": "current"
        },
        {
          "cacheTimeout": null,
          "colorBackground": false,
          "colorValue": false,
          "colors": [
            "#299c46",
            "rgba(237, 129, 40, 0.89)",
            "#d44a3a"
          ],
          "datasource": "RANCHER_MONITORING",
          "fieldConfig": {
            "defaults": {
              "custom": {}
            },
            "overrides": []
          },
          "format": "none",
          "gauge": {
            "maxValue": 500,
            "minValue": 0,
            "show": true,
            "thresholdLabels": false,
            "thresholdMarkers": true
          },
          "gridPos": {
            "h": 7,
            "w": 8,
            "x": 16,
            "y": 66
          },
          "id": 233,
          "interval": null,
          "links": [],
          "mappingType": 1,
          "mappingTypes": [
            {
              "name": "value to text",
              "value": 1
            },
            {
              "name": "range to text",
              "value": 2
            }
          ],
          "maxDataPoints": 100,
          "nullPointMode": "connected",
          "nullText": null,
          "postfix": "",
          "postfixFontSize": "50%",
          "prefix": "",
          "prefixFontSize": "50%",
          "rangeMaps": [
            {
              "from": "null",
              "text": "N/A",
              "to": "null"
            }
          ],
          "sparkline": {
            "fillColor": "rgba(31, 118, 189, 0.18)",
            "full": false,
            "lineColor": "rgb(31, 120, 193)",
            "show": true
          },
          "tableColumn": "",
          "targets": [
            {
              "expr": "avg(oracledb_redo{database='$database'})",
              "format": "time_series",
              "intervalFactor": 2,
              "refId": "A"
            }
          ],
          "thresholds": "200,300,400",
          "title": "Redolog Switches in Last 5 min",
          "type": "singlestat",
          "valueFontSize": "80%",
          "valueMaps": [
            {
              "op": "=",
              "text": "N/A",
              "value": "null"
            }
          ],
          "valueName": "current"
        },
        {
          "aliasColors": {},
          "bars": false,
          "dashLength": 10,
          "dashes": false,
          "datasource": "RANCHER_MONITORING",
          "fieldConfig": {
            "defaults": {
              "custom": {}
            },
            "overrides": []
          },
          "fill": 1,
          "fillGradient": 0,
          "gridPos": {
            "h": 6,
            "w": 24,
            "x": 0,
            "y": 73
          },
          "hiddenSeries": false,
          "id": 273,
          "legend": {
            "alignAsTable": false,
            "avg": false,
            "current": true,
            "hideEmpty": false,
            "hideZero": true,
            "max": true,
            "min": true,
            "rightSide": true,
            "show": true,
            "total": false,
            "values": true
          },
          "lines": true,
          "linewidth": 1,
          "links": [],
          "nullPointMode": "null",
          "options": {
            "dataLinks": []
          },
          "percentage": false,
          "pointradius": 5,
          "points": false,
          "renderer": "flot",
          "seriesOverrides": [],
          "spaceLength": 10,
          "stack": false,
          "steppedLine": false,
          "targets": [
            {
              "expr": "avg(oracledb_recovery{database='$database',type=\"percent_space_used\"})",
              "format": "time_series",
              "intervalFactor": 2,
              "legendFormat": "Used",
              "refId": "A"
            },
            {
              "expr": "avg(oracledb_recovery{database='$database',type=\"percent_space_reclaimable\"})",
              "format": "time_series",
              "intervalFactor": 2,
              "legendFormat": "Reclaimable",
              "refId": "B"
            }
          ],
          "thresholds": [],
          "timeFrom": null,
          "timeRegions": [],
          "timeShift": null,
          "title": "FRA Usage",
          "tooltip": {
            "shared": true,
            "sort": 0,
            "value_type": "individual"
          },
          "type": "graph",
          "xaxis": {
            "buckets": null,
            "mode": "time",
            "name": null,
            "show": true,
            "values": []
          },
          "yaxes": [
            {
              "decimals": 1,
              "format": "short",
              "label": "",
              "logBase": 1,
              "max": "100",
              "min": "0",
              "show": true
            },
            {
              "format": "short",
              "label": null,
              "logBase": 1,
              "max": null,
              "min": null,
              "show": true
            }
          ],
          "yaxis": {
            "align": false,
            "alignLevel": null
          }
        }
      ],
      "title": "Oracle FRA",
      "type": "row"
    },
    {
      "collapsed": true,
      "datasource": "RANCHER_MONITORING",
      "gridPos": {
        "h": 1,
        "w": 24,
        "x": 0,
        "y": 11
      },
      "id": 285,
      "panels": [
        {
          "aliasColors": {},
          "bars": false,
          "dashLength": 10,
          "dashes": false,
          "datasource": "RANCHER_MONITORING",
          "decimals": null,
          "editable": true,
          "error": false,
          "fieldConfig": {
            "defaults": {
              "custom": {}
            },
            "overrides": []
          },
          "fill": 2,
          "fillGradient": 0,
          "grid": {},
          "gridPos": {
            "h": 9,
            "w": 12,
            "x": 0,
            "y": 80
          },
          "hiddenSeries": false,
          "id": 275,
          "legend": {
            "alignAsTable": false,
            "avg": false,
            "current": false,
            "max": false,
            "min": false,
            "rightSide": false,
            "show": true,
            "total": false,
            "values": false
          },
          "lines": true,
          "linewidth": 2,
          "links": [],
          "maxPerRow": 4,
          "nullPointMode": "null",
          "options": {
            "dataLinks": []
          },
          "percentage": false,
          "pointradius": 5,
          "points": false,
          "renderer": "flot",
          "repeat": null,
          "seriesOverrides": [],
          "spaceLength": 10,
          "stack": true,
          "steppedLine": false,
          "targets": [
            {
              "expr": "avg(oracledb_waitclass{dbinstance=~'$dbinstance'}) without (job)",
              "format": "time_series",
              "intervalFactor": 2,
              "legendFormat": "{{type}}",
              "refId": "H"
            }
          ],
          "thresholds": [],
          "timeFrom": null,
          "timeRegions": [],
          "timeShift": null,
          "title": "Wait Events $dbinstance",
          "tooltip": {
            "msResolution": false,
            "shared": true,
            "sort": 0,
            "value_type": "individual"
          },
          "type": "graph",
          "xaxis": {
            "buckets": null,
            "mode": "time",
            "name": null,
            "show": true,
            "values": []
          },
          "yaxes": [
            {
              "format": "short",
              "logBase": 1,
              "max": null,
              "min": 0,
              "show": true
            },
            {
              "format": "short",
              "logBase": 1,
              "max": null,
              "min": 0,
              "show": false
            }
          ],
          "yaxis": {
            "align": false,
            "alignLevel": null
          }
        },
        {
          "aliasColors": {},
          "bars": false,
          "dashLength": 10,
          "dashes": false,
          "datasource": "RANCHER_MONITORING",
          "fieldConfig": {
            "defaults": {
              "custom": {}
            },
            "overrides": []
          },
          "fill": 1,
          "fillGradient": 0,
          "gridPos": {
            "h": 9,
            "w": 12,
            "x": 12,
            "y": 80
          },
          "hiddenSeries": false,
          "id": 277,
          "legend": {
            "avg": false,
            "current": false,
            "max": false,
            "min": false,
            "show": true,
            "total": false,
            "values": false
          },
          "lines": true,
          "linewidth": 1,
          "links": [],
          "maxPerRow": 4,
          "nullPointMode": "null",
          "options": {
            "dataLinks": []
          },
          "percentage": false,
          "pointradius": 5,
          "points": false,
          "renderer": "flot",
          "repeat": null,
          "seriesOverrides": [],
          "spaceLength": 10,
          "stack": false,
          "steppedLine": false,
          "targets": [
            {
              "expr": "avg(rate(oracledb_interconnect{dbinstance=~'$dbinstance'}[5m])) without (job)",
              "format": "time_series",
              "intervalFactor": 2,
              "legendFormat": "{{type}}",
              "refId": "A"
            }
          ],
          "thresholds": [],
          "timeFrom": null,
          "timeRegions": [],
          "timeShift": null,
          "title": "Interconnect  Block Transfer $dbinstance",
          "tooltip": {
            "shared": true,
            "sort": 0,
            "value_type": "individual"
          },
          "type": "graph",
          "xaxis": {
            "buckets": null,
            "mode": "time",
            "name": null,
            "show": true,
            "values": []
          },
          "yaxes": [
            {
              "decimals": null,
              "format": "none",
              "label": null,
              "logBase": 1,
              "max": null,
              "min": null,
              "show": true
            },
            {
              "format": "ms",
              "label": null,
              "logBase": 1,
              "max": null,
              "min": null,
              "show": false
            }
          ],
          "yaxis": {
            "align": false,
            "alignLevel": null
          }
        },
        {
          "aliasColors": {},
          "bars": false,
          "dashLength": 10,
          "dashes": false,
          "datasource": "RANCHER_MONITORING",
          "fieldConfig": {
            "defaults": {
              "custom": {}
            },
            "overrides": []
          },
          "fill": 1,
          "fillGradient": 0,
          "gridPos": {
            "h": 8,
            "w": 12,
            "x": 0,
            "y": 89
          },
          "hiddenSeries": false,
          "id": 281,
          "legend": {
            "alignAsTable": true,
            "avg": false,
            "current": false,
            "max": true,
            "min": true,
            "show": true,
            "total": false,
            "values": true
          },
          "lines": true,
          "linewidth": 1,
          "links": [],
          "maxPerRow": 4,
          "nullPointMode": "null",
          "options": {
            "dataLinks": []
          },
          "percentage": false,
          "pointradius": 5,
          "points": false,
          "renderer": "flot",
          "repeat": null,
          "seriesOverrides": [],
          "spaceLength": 10,
          "stack": false,
          "steppedLine": false,
          "targets": [
            {
              "expr": "avg(oracledb_sysmetric{dbinstance=~'$dbinstance',type=~'.*bytes.*'}) without (job)",
              "format": "time_series",
              "intervalFactor": 2,
              "legendFormat": "{{type}}",
              "refId": "A"
            }
          ],
          "thresholds": [],
          "timeFrom": null,
          "timeRegions": [],
          "timeShift": null,
          "title": "Physical Throughput $dbinstance",
          "tooltip": {
            "shared": true,
            "sort": 0,
            "value_type": "individual"
          },
          "type": "graph",
          "xaxis": {
            "buckets": null,
            "mode": "time",
            "name": null,
            "show": true,
            "values": []
          },
          "yaxes": [
            {
              "format": "Bps",
              "label": null,
              "logBase": 1,
              "max": null,
              "min": null,
              "show": true
            },
            {
              "format": "short",
              "label": null,
              "logBase": 1,
              "max": null,
              "min": null,
              "show": true
            }
          ],
          "yaxis": {
            "align": false,
            "alignLevel": null
          }
        },
        {
          "aliasColors": {},
          "bars": false,
          "dashLength": 10,
          "dashes": false,
          "datasource": "RANCHER_MONITORING",
          "fieldConfig": {
            "defaults": {
              "custom": {}
            },
            "overrides": []
          },
          "fill": 1,
          "fillGradient": 0,
          "gridPos": {
            "h": 8,
            "w": 12,
            "x": 12,
            "y": 89
          },
          "hiddenSeries": false,
          "id": 283,
          "legend": {
            "alignAsTable": true,
            "avg": true,
            "current": true,
            "max": false,
            "min": false,
            "show": true,
            "total": false,
            "values": true
          },
          "lines": true,
          "linewidth": 1,
          "links": [],
          "maxPerRow": 4,
          "nullPointMode": "null",
          "options": {
            "dataLinks": []
          },
          "percentage": false,
          "pointradius": 5,
          "points": false,
          "renderer": "flot",
          "repeat": null,
          "seriesOverrides": [],
          "spaceLength": 10,
          "stack": true,
          "steppedLine": false,
          "targets": [
            {
              "expr": "avg(oracledb_sysmetric{dbinstance=~'$dbinstance',type=~'.*requests.*'}) without (job)",
              "format": "time_series",
              "intervalFactor": 2,
              "legendFormat": "{{type}}",
              "refId": "A"
            }
          ],
          "thresholds": [],
          "timeFrom": null,
          "timeRegions": [],
          "timeShift": null,
          "title": "Physical IOPs $dbinstance",
          "tooltip": {
            "shared": true,
            "sort": 0,
            "value_type": "individual"
          },
          "type": "graph",
          "xaxis": {
            "buckets": null,
            "mode": "time",
            "name": null,
            "show": true,
            "values": []
          },
          "yaxes": [
            {
              "format": "iops",
              "label": null,
              "logBase": 1,
              "max": null,
              "min": null,
              "show": true
            },
            {
              "format": "short",
              "label": null,
              "logBase": 1,
              "max": null,
              "min": null,
              "show": false
            }
          ],
          "yaxis": {
            "align": false,
            "alignLevel": null
          }
        }
      ],
      "title": "Oracle transfer RAC",
      "type": "row"
    },
    {
      "collapsed": true,
      "datasource": "RANCHER_MONITORING",
      "gridPos": {
        "h": 1,
        "w": 24,
        "x": 0,
        "y": 12
      },
      "id": 295,
      "panels": [
        {
          "aliasColors": {},
          "bars": false,
          "dashLength": 10,
          "dashes": false,
          "datasource": "RANCHER_MONITORING",
          "decimals": null,
          "editable": true,
          "error": false,
          "fieldConfig": {
            "defaults": {
              "custom": {}
            },
            "overrides": []
          },
          "fill": 2,
          "fillGradient": 0,
          "grid": {},
          "gridPos": {
            "h": 8,
            "w": 12,
            "x": 0,
            "y": 7
          },
          "hiddenSeries": false,
          "id": 287,
          "legend": {
            "alignAsTable": false,
            "avg": false,
            "current": false,
            "max": false,
            "min": false,
            "rightSide": false,
            "show": true,
            "total": false,
            "values": false
          },
          "lines": true,
          "linewidth": 2,
          "links": [],
          "maxPerRow": 1,
          "nullPointMode": "null",
          "options": {
            "dataLinks": []
          },
          "percentage": false,
          "pointradius": 5,
          "points": false,
          "renderer": "flot",
          "repeat": null,
          "seriesOverrides": [],
          "spaceLength": 10,
          "stack": true,
          "steppedLine": false,
          "targets": [
            {
              "expr": "sum(oracledb_waitclass{database='$database'}) without (instance,dbinstance,job)",
              "format": "time_series",
              "intervalFactor": 2,
              "legendFormat": "{{type}}",
              "refId": "H"
            }
          ],
          "thresholds": [],
          "timeFrom": null,
          "timeRegions": [],
          "timeShift": null,
          "title": "Wait Events $database",
          "tooltip": {
            "msResolution": false,
            "shared": true,
            "sort": 0,
            "value_type": "individual"
          },
          "type": "graph",
          "xaxis": {
            "buckets": null,
            "mode": "time",
            "name": null,
            "show": true,
            "values": []
          },
          "yaxes": [
            {
              "format": "short",
              "logBase": 1,
              "max": null,
              "min": 0,
              "show": true
            },
            {
              "format": "short",
              "logBase": 1,
              "max": null,
              "min": 0,
              "show": false
            }
          ],
          "yaxis": {
            "align": false,
            "alignLevel": null
          }
        },
        {
          "aliasColors": {},
          "bars": false,
          "dashLength": 10,
          "dashes": false,
          "datasource": "RANCHER_MONITORING",
          "fieldConfig": {
            "defaults": {
              "custom": {}
            },
            "overrides": []
          },
          "fill": 1,
          "fillGradient": 0,
          "gridPos": {
            "h": 8,
            "w": 12,
            "x": 12,
            "y": 7
          },
          "hiddenSeries": false,
          "id": 289,
          "legend": {
            "avg": false,
            "current": false,
            "max": false,
            "min": false,
            "show": true,
            "total": false,
            "values": false
          },
          "lines": true,
          "linewidth": 1,
          "links": [],
          "maxPerRow": 1,
          "nullPointMode": "null",
          "options": {
            "dataLinks": []
          },
          "percentage": false,
          "pointradius": 5,
          "points": false,
          "renderer": "flot",
          "repeat": null,
          "seriesOverrides": [],
          "spaceLength": 10,
          "stack": false,
          "steppedLine": false,
          "targets": [
            {
              "expr": "avg(sum(rate(oracledb_interconnect{database='$database'}[5m])) without (instance)) without (job)",
              "format": "time_series",
              "intervalFactor": 2,
              "legendFormat": "{{dbinstance}}:{{type}}",
              "refId": "A"
            }
          ],
          "thresholds": [],
          "timeFrom": null,
          "timeRegions": [],
          "timeShift": null,
          "title": "Interconnect Block Transfer $database",
          "tooltip": {
            "shared": true,
            "sort": 0,
            "value_type": "individual"
          },
          "type": "graph",
          "xaxis": {
            "buckets": null,
            "mode": "time",
            "name": null,
            "show": true,
            "values": []
          },
          "yaxes": [
            {
              "decimals": null,
              "format": "none",
              "label": null,
              "logBase": 1,
              "max": null,
              "min": "0",
              "show": true
            },
            {
              "format": "ms",
              "label": null,
              "logBase": 1,
              "max": null,
              "min": null,
              "show": false
            }
          ],
          "yaxis": {
            "align": false,
            "alignLevel": null
          }
        },
        {
          "aliasColors": {},
          "bars": false,
          "dashLength": 10,
          "dashes": false,
          "datasource": "RANCHER_MONITORING",
          "fieldConfig": {
            "defaults": {
              "custom": {}
            },
            "overrides": []
          },
          "fill": 1,
          "fillGradient": 0,
          "gridPos": {
            "h": 7,
            "w": 12,
            "x": 0,
            "y": 15
          },
          "hiddenSeries": false,
          "id": 291,
          "legend": {
            "avg": false,
            "current": false,
            "max": false,
            "min": false,
            "show": true,
            "total": false,
            "values": false
          },
          "lines": true,
          "linewidth": 1,
          "links": [],
          "maxPerRow": 1,
          "nullPointMode": "null",
          "options": {
            "dataLinks": []
          },
          "percentage": false,
          "pointradius": 5,
          "points": false,
          "renderer": "flot",
          "repeat": null,
          "seriesOverrides": [],
          "spaceLength": 10,
          "stack": false,
          "steppedLine": false,
          "targets": [
            {
              "expr": "avg(sum(oracledb_sysmetric{database='$database',type=~'.*bytes.*'}) without (instance,dbinstance)) without (job)",
              "format": "time_series",
              "intervalFactor": 2,
              "legendFormat": "{{type}}",
              "refId": "A"
            }
          ],
          "thresholds": [],
          "timeFrom": null,
          "timeRegions": [],
          "timeShift": null,
          "title": "Physical Throughput $database",
          "tooltip": {
            "shared": true,
            "sort": 0,
            "value_type": "individual"
          },
          "type": "graph",
          "xaxis": {
            "buckets": null,
            "mode": "time",
            "name": null,
            "show": true,
            "values": []
          },
          "yaxes": [
            {
              "format": "Bps",
              "label": null,
              "logBase": 1,
              "max": null,
              "min": null,
              "show": true
            },
            {
              "format": "short",
              "label": null,
              "logBase": 1,
              "max": null,
              "min": null,
              "show": true
            }
          ],
          "yaxis": {
            "align": false,
            "alignLevel": null
          }
        },
        {
          "aliasColors": {},
          "bars": false,
          "dashLength": 10,
          "dashes": false,
          "datasource": "RANCHER_MONITORING",
          "fieldConfig": {
            "defaults": {
              "custom": {}
            },
            "overrides": []
          },
          "fill": 1,
          "fillGradient": 0,
          "gridPos": {
            "h": 7,
            "w": 12,
            "x": 12,
            "y": 15
          },
          "hiddenSeries": false,
          "id": 293,
          "legend": {
            "alignAsTable": true,
            "avg": true,
            "current": true,
            "max": true,
            "min": true,
            "show": true,
            "total": false,
            "values": true
          },
          "lines": true,
          "linewidth": 1,
          "links": [],
          "maxPerRow": 1,
          "nullPointMode": "null",
          "options": {
            "dataLinks": []
          },
          "percentage": false,
          "pointradius": 5,
          "points": false,
          "renderer": "flot",
          "repeat": null,
          "seriesOverrides": [],
          "spaceLength": 10,
          "stack": true,
          "steppedLine": false,
          "targets": [
            {
              "expr": "avg(sum(oracledb_sysmetric{database='$database',type=~'.*requests.*'}) without (instance,dbinstance)) without (job)",
              "format": "time_series",
              "intervalFactor": 2,
              "legendFormat": "{{type}}",
              "refId": "A"
            }
          ],
          "thresholds": [],
          "timeFrom": null,
          "timeRegions": [],
          "timeShift": null,
          "title": "Physical IOPs $database",
          "tooltip": {
            "shared": true,
            "sort": 0,
            "value_type": "individual"
          },
          "type": "graph",
          "xaxis": {
            "buckets": null,
            "mode": "time",
            "name": null,
            "show": true,
            "values": []
          },
          "yaxes": [
            {
              "format": "iops",
              "label": null,
              "logBase": 1,
              "max": null,
              "min": null,
              "show": true
            },
            {
              "format": "short",
              "label": null,
              "logBase": 1,
              "max": null,
              "min": null,
              "show": false
            }
          ],
          "yaxis": {
            "align": false,
            "alignLevel": null
          }
        }
      ],
      "title": "Oracle transfer",
      "type": "row"
    },
    {
      "collapsed": true,
      "datasource": "RANCHER_MONITORING",
      "gridPos": {
        "h": 1,
        "w": 24,
        "x": 0,
        "y": 13
      },
      "id": 299,
      "panels": [
        {
          "cacheTimeout": null,
          "columns": [],
          "datasource": "RANCHER_MONITORING",
          "fieldConfig": {
            "defaults": {
              "custom": {}
            },
            "overrides": []
          },
          "fontSize": "90%",
          "gridPos": {
            "h": 9,
            "w": 24,
            "x": 0,
            "y": 14
          },
          "id": 301,
          "links": [],
          "pageSize": null,
          "repeat": null,
          "repeatDirection": null,
          "scroll": true,
          "showHeader": true,
          "sort": {
            "col": 7,
            "desc": true
          },
          "styles": [
            {
              "alias": "Time",
              "align": "auto",
              "dateFormat": "YYYY-MM-DD HH:mm:ss",
              "pattern": "Time",
              "type": "hidden"
            },
            {
              "alias": "Database",
              "align": "auto",
              "colorMode": null,
              "colors": [
                "rgba(245, 54, 54, 0.9)",
                "rgba(237, 129, 40, 0.89)",
                "rgba(50, 172, 45, 0.97)"
              ],
              "dateFormat": "YYYY-MM-DD HH:mm:ss",
              "decimals": 2,
              "link": false,
              "mappingType": 1,
              "pattern": "descr",
              "preserveFormat": false,
              "thresholds": [],
              "type": "hidden",
              "unit": "short"
            },
            {
              "alias": "Table space",
              "align": "auto",
              "colorMode": null,
              "colors": [
                "rgba(245, 54, 54, 0.9)",
                "rgba(237, 129, 40, 0.89)",
                "rgba(50, 172, 45, 0.97)"
              ],
              "dateFormat": "YYYY-MM-DD HH:mm:ss",
              "decimals": 2,
              "link": false,
              "mappingType": 1,
              "pattern": "tablespace",
              "sanitize": false,
              "thresholds": [],
              "type": "string",
              "unit": "short",
              "valueMaps": []
            },
            {
              "alias": "Table space type",
              "align": "auto",
              "colorMode": null,
              "colors": [
                "rgba(245, 54, 54, 0.9)",
                "rgba(237, 129, 40, 0.89)",
                "rgba(50, 172, 45, 0.97)"
              ],
              "dateFormat": "YYYY-MM-DD HH:mm:ss",
              "decimals": 2,
              "mappingType": 1,
              "pattern": "type",
              "thresholds": [
                ""
              ],
              "type": "string",
              "unit": "short",
              "valueMaps": [
                {
                  "text": "PERMANENT",
                  "value": "PERMANENT"
                },
                {
                  "text": "UNDO",
                  "value": "UNDO"
                },
                {
                  "text": "TEMPORARY",
                  "value": "TEMPORARY"
                }
              ]
            },
            {
              "alias": "Usage Rate",
              "align": "auto",
              "colorMode": "cell",
              "colors": [
                "rgba(50, 172, 45, 0.97)",
                "rgba(237, 129, 40, 0.89)",
                "rgba(245, 54, 54, 0.9)"
              ],
              "dateFormat": "YYYY-MM-DD HH:mm:ss",
              "decimals": 3,
              "mappingType": 1,
              "pattern": "Value #A",
              "thresholds": [
                "0.75",
                "0.95"
              ],
              "type": "number",
              "unit": "percentunit"
            },
            {
              "alias": "Remaining Space",
              "align": "auto",
              "colorMode": null,
              "colors": [
                "rgba(245, 54, 54, 0.9)",
                "rgba(237, 129, 40, 0.89)",
                "rgba(50, 172, 45, 0.97)"
              ],
              "dateFormat": "YYYY-MM-DD HH:mm:ss",
              "decimals": 2,
              "mappingType": 1,
              "pattern": "Value #B",
              "thresholds": [],
              "type": "number",
              "unit": "bytes"
            },
            {
              "alias": "",
              "align": "auto",
              "colorMode": null,
              "colors": [
                "rgba(245, 54, 54, 0.9)",
                "rgba(237, 129, 40, 0.89)",
                "rgba(50, 172, 45, 0.97)"
              ],
              "decimals": 2,
              "pattern": "/.*/",
              "thresholds": [],
              "type": "hidden",
              "unit": "short"
            }
          ],
          "targets": [
            {
              "expr": "1-(oracledb_tablespace_free{instance=\"$host\"}/oracledb_tablespace_max_bytes{instance=\"$host\"})",
              "format": "table",
              "hide": false,
              "instant": true,
              "intervalFactor": 1,
              "legendFormat": "",
              "refId": "A"
            },
            {
              "expr": "oracledb_tablespace_free{instance=\"$host\"}",
              "format": "table",
              "instant": true,
              "intervalFactor": 1,
              "refId": "B"
            }
          ],
          "timeFrom": null,
          "timeShift": null,
          "title": "Table space status",
          "transform": "table",
          "type": "table"
        }
      ],
      "repeat": null,
      "title": "Oracle tablespace",
      "type": "row"
    },
    {
      "collapsed": true,
      "datasource": "RANCHER_MONITORING",
      "gridPos": {
        "h": 1,
        "w": 24,
        "x": 0,
        "y": 14
      },
      "id": 305,
      "panels": [
        {
          "columns": [],
          "datasource": "RANCHER_MONITORING",
          "fieldConfig": {
            "defaults": {
              "custom": {}
            },
            "overrides": []
          },
          "fontSize": "100%",
          "gridPos": {
            "h": 10,
            "w": 12,
            "x": 0,
            "y": 15
          },
          "id": 303,
          "links": [],
          "pageSize": null,
          "scroll": true,
          "showHeader": true,
          "sort": {
            "col": 0,
            "desc": true
          },
          "styles": [
            {
              "alias": "",
              "align": "auto",
              "colorMode": null,
              "colors": [
                "rgba(245, 54, 54, 0.9)",
                "rgba(237, 129, 40, 0.89)",
                "rgba(50, 172, 45, 0.97)"
              ],
              "dateFormat": "YYYY-MM-DD HH:mm:ss",
              "decimals": 2,
              "pattern": "database",
              "thresholds": [],
              "type": "hidden",
              "unit": "short"
            },
            {
              "alias": "",
              "align": "auto",
              "colorMode": null,
              "colors": [
                "rgba(245, 54, 54, 0.9)",
                "rgba(237, 129, 40, 0.89)",
                "rgba(50, 172, 45, 0.97)"
              ],
              "dateFormat": "YYYY-MM-DD HH:mm:ss",
              "decimals": 2,
              "pattern": "environment",
              "thresholds": [],
              "type": "hidden",
              "unit": "short"
            },
            {
              "alias": "Host",
              "align": "auto",
              "colorMode": null,
              "colors": [
                "rgba(245, 54, 54, 0.9)",
                "rgba(237, 129, 40, 0.89)",
                "rgba(50, 172, 45, 0.97)"
              ],
              "dateFormat": "YYYY-MM-DD HH:mm:ss",
              "decimals": 2,
              "pattern": "instance",
              "thresholds": [],
              "type": "string",
              "unit": "short"
            },
            {
              "alias": "",
              "align": "auto",
              "colorMode": null,
              "colors": [
                "rgba(245, 54, 54, 0.9)",
                "rgba(237, 129, 40, 0.89)",
                "rgba(50, 172, 45, 0.97)"
              ],
              "dateFormat": "YYYY-MM-DD HH:mm:ss",
              "decimals": 2,
              "pattern": "job",
              "thresholds": [],
              "type": "hidden",
              "unit": "short"
            },
            {
              "alias": "",
              "align": "auto",
              "colorMode": null,
              "colors": [
                "rgba(245, 54, 54, 0.9)",
                "rgba(237, 129, 40, 0.89)",
                "rgba(50, 172, 45, 0.97)"
              ],
              "dateFormat": "YYYY-MM-DD HH:mm:ss",
              "decimals": 2,
              "pattern": "__name__",
              "thresholds": [],
              "type": "hidden",
              "unit": "short"
            },
            {
              "alias": "",
              "align": "auto",
              "colorMode": null,
              "colors": [
                "rgba(245, 54, 54, 0.9)",
                "rgba(237, 129, 40, 0.89)",
                "rgba(50, 172, 45, 0.97)"
              ],
              "dateFormat": "YYYY-MM-DD HH:mm:ss",
              "decimals": 2,
              "link": false,
              "pattern": "Time",
              "thresholds": [],
              "type": "date",
              "unit": "short"
            },
            {
              "alias": "Count",
              "align": "auto",
              "colorMode": null,
              "colors": [
                "rgba(245, 54, 54, 0.9)",
                "rgba(237, 129, 40, 0.89)",
                "rgba(50, 172, 45, 0.97)"
              ],
              "dateFormat": "YYYY-MM-DD HH:mm:ss",
              "decimals": 0,
              "pattern": "Value",
              "thresholds": [],
              "type": "number",
              "unit": "short"
            },
            {
              "alias": "Instance",
              "align": "auto",
              "colorMode": null,
              "colors": [
                "rgba(245, 54, 54, 0.9)",
                "rgba(237, 129, 40, 0.89)",
                "rgba(50, 172, 45, 0.97)"
              ],
              "dateFormat": "YYYY-MM-DD HH:mm:ss",
              "decimals": 2,
              "pattern": "dbinstance",
              "thresholds": [],
              "type": "number",
              "unit": "short"
            },
            {
              "alias": "",
              "align": "auto",
              "colorMode": null,
              "colors": [
                "rgba(245, 54, 54, 0.9)",
                "rgba(237, 129, 40, 0.89)",
                "rgba(50, 172, 45, 0.97)"
              ],
              "dateFormat": "YYYY-MM-DD HH:mm:ss",
              "decimals": 2,
              "pattern": "ignore",
              "thresholds": [],
              "type": "hidden",
              "unit": "short"
            },
            {
              "alias": "Error Description",
              "align": "auto",
              "colorMode": null,
              "colors": [
                "rgba(245, 54, 54, 0.9)",
                "rgba(237, 129, 40, 0.89)",
                "rgba(50, 172, 45, 0.97)"
              ],
              "dateFormat": "YYYY-MM-DD HH:mm:ss",
              "decimals": 2,
              "pattern": "description",
              "thresholds": [],
              "type": "number",
              "unit": "short"
            },
            {
              "alias": "Eror Code",
              "align": "auto",
              "colorMode": null,
              "colors": [
                "rgba(245, 54, 54, 0.9)",
                "rgba(237, 129, 40, 0.89)",
                "rgba(50, 172, 45, 0.97)"
              ],
              "dateFormat": "YYYY-MM-DD HH:mm:ss",
              "decimals": 2,
              "pattern": "code",
              "thresholds": [],
              "type": "number",
              "unit": "short"
            }
          ],
          "targets": [
            {
              "expr": "oracledb_error{dbinstance=~'$dbinstance',ignore=\"0\"}",
              "format": "table",
              "hide": false,
              "instant": false,
              "interval": "",
              "intervalFactor": 1,
              "legendFormat": "",
              "refId": "A"
            }
          ],
          "title": "Valid Errors",
          "transform": "table",
          "type": "table"
        },
        {
          "columns": [],
          "datasource": "RANCHER_MONITORING",
          "fieldConfig": {
            "defaults": {
              "custom": {}
            },
            "overrides": []
          },
          "fontSize": "100%",
          "gridPos": {
            "h": 10,
            "w": 12,
            "x": 12,
            "y": 15
          },
          "id": 307,
          "links": [],
          "pageSize": null,
          "scroll": true,
          "showHeader": true,
          "sort": {
            "col": 0,
            "desc": true
          },
          "styles": [
            {
              "alias": "",
              "align": "auto",
              "colorMode": null,
              "colors": [
                "rgba(245, 54, 54, 0.9)",
                "rgba(237, 129, 40, 0.89)",
                "rgba(50, 172, 45, 0.97)"
              ],
              "dateFormat": "YYYY-MM-DD HH:mm:ss",
              "decimals": 2,
              "pattern": "database",
              "thresholds": [],
              "type": "hidden",
              "unit": "short"
            },
            {
              "alias": "",
              "align": "auto",
              "colorMode": null,
              "colors": [
                "rgba(245, 54, 54, 0.9)",
                "rgba(237, 129, 40, 0.89)",
                "rgba(50, 172, 45, 0.97)"
              ],
              "dateFormat": "YYYY-MM-DD HH:mm:ss",
              "decimals": 2,
              "pattern": "environment",
              "thresholds": [],
              "type": "hidden",
              "unit": "short"
            },
            {
              "alias": "Host",
              "align": "auto",
              "colorMode": null,
              "colors": [
                "rgba(245, 54, 54, 0.9)",
                "rgba(237, 129, 40, 0.89)",
                "rgba(50, 172, 45, 0.97)"
              ],
              "dateFormat": "YYYY-MM-DD HH:mm:ss",
              "decimals": 2,
              "pattern": "instance",
              "thresholds": [],
              "type": "string",
              "unit": "short"
            },
            {
              "alias": "",
              "align": "auto",
              "colorMode": null,
              "colors": [
                "rgba(245, 54, 54, 0.9)",
                "rgba(237, 129, 40, 0.89)",
                "rgba(50, 172, 45, 0.97)"
              ],
              "dateFormat": "YYYY-MM-DD HH:mm:ss",
              "decimals": 2,
              "pattern": "job",
              "thresholds": [],
              "type": "hidden",
              "unit": "short"
            },
            {
              "alias": "",
              "align": "auto",
              "colorMode": null,
              "colors": [
                "rgba(245, 54, 54, 0.9)",
                "rgba(237, 129, 40, 0.89)",
                "rgba(50, 172, 45, 0.97)"
              ],
              "dateFormat": "YYYY-MM-DD HH:mm:ss",
              "decimals": 2,
              "pattern": "__name__",
              "thresholds": [],
              "type": "hidden",
              "unit": "short"
            },
            {
              "alias": "",
              "align": "auto",
              "colorMode": null,
              "colors": [
                "rgba(245, 54, 54, 0.9)",
                "rgba(237, 129, 40, 0.89)",
                "rgba(50, 172, 45, 0.97)"
              ],
              "dateFormat": "YYYY-MM-DD HH:mm:ss",
              "decimals": 2,
              "link": false,
              "pattern": "Time",
              "thresholds": [],
              "type": "date",
              "unit": "short"
            },
            {
              "alias": "Count",
              "align": "auto",
              "colorMode": null,
              "colors": [
                "rgba(245, 54, 54, 0.9)",
                "rgba(237, 129, 40, 0.89)",
                "rgba(50, 172, 45, 0.97)"
              ],
              "dateFormat": "YYYY-MM-DD HH:mm:ss",
              "decimals": 0,
              "pattern": "Value",
              "thresholds": [],
              "type": "number",
              "unit": "short"
            },
            {
              "alias": "Instance",
              "align": "auto",
              "colorMode": null,
              "colors": [
                "rgba(245, 54, 54, 0.9)",
                "rgba(237, 129, 40, 0.89)",
                "rgba(50, 172, 45, 0.97)"
              ],
              "dateFormat": "YYYY-MM-DD HH:mm:ss",
              "decimals": 2,
              "pattern": "dbinstance",
              "thresholds": [],
              "type": "number",
              "unit": "short"
            },
            {
              "alias": "",
              "align": "auto",
              "colorMode": null,
              "colors": [
                "rgba(245, 54, 54, 0.9)",
                "rgba(237, 129, 40, 0.89)",
                "rgba(50, 172, 45, 0.97)"
              ],
              "dateFormat": "YYYY-MM-DD HH:mm:ss",
              "decimals": 2,
              "pattern": "ignore",
              "thresholds": [],
              "type": "hidden",
              "unit": "short"
            },
            {
              "alias": "Error Description",
              "align": "auto",
              "colorMode": null,
              "colors": [
                "rgba(245, 54, 54, 0.9)",
                "rgba(237, 129, 40, 0.89)",
                "rgba(50, 172, 45, 0.97)"
              ],
              "dateFormat": "YYYY-MM-DD HH:mm:ss",
              "decimals": 2,
              "pattern": "description",
              "thresholds": [],
              "type": "number",
              "unit": "short"
            },
            {
              "alias": "Error Code",
              "align": "auto",
              "colorMode": null,
              "colors": [
                "rgba(245, 54, 54, 0.9)",
                "rgba(237, 129, 40, 0.89)",
                "rgba(50, 172, 45, 0.97)"
              ],
              "dateFormat": "YYYY-MM-DD HH:mm:ss",
              "decimals": 2,
              "pattern": "code",
              "thresholds": [],
              "type": "number",
              "unit": "short"
            }
          ],
          "targets": [
            {
              "expr": "oracledb_error{dbinstance=~'$dbinstance',ignore=\"1\"}",
              "format": "table",
              "hide": false,
              "instant": false,
              "intervalFactor": 1,
              "legendFormat": "",
              "refId": "A"
            }
          ],
          "title": "Ignored Errors",
          "transform": "table",
          "type": "table"
        },
        {
          "aliasColors": {},
          "bars": false,
          "dashLength": 10,
          "dashes": false,
          "datasource": "RANCHER_MONITORING",
          "fieldConfig": {
            "defaults": {
              "custom": {}
            },
            "overrides": []
          },
          "fill": 1,
          "fillGradient": 0,
          "gridPos": {
            "h": 5,
            "w": 24,
            "x": 0,
            "y": 25
          },
          "hiddenSeries": false,
          "id": 309,
          "legend": {
            "alignAsTable": false,
            "avg": false,
            "current": false,
            "hideEmpty": false,
            "hideZero": false,
            "max": false,
            "min": false,
            "rightSide": false,
            "show": true,
            "total": false,
            "values": false
          },
          "lines": true,
          "linewidth": 1,
          "links": [],
          "maxPerRow": 12,
          "nullPointMode": "null",
          "options": {
            "dataLinks": []
          },
          "percentage": false,
          "pointradius": 5,
          "points": false,
          "renderer": "flot",
          "repeat": null,
          "repeatDirection": "h",
          "seriesOverrides": [],
          "spaceLength": 10,
          "stack": false,
          "steppedLine": false,
          "targets": [
            {
              "expr": "time() - avg(oracledb_error_unix_seconds{database!='+ASM',dbinstance=~'$dbinstance'}) without (job)",
              "format": "time_series",
              "intervalFactor": 1,
              "legendFormat": "{{dbinstance}}",
              "refId": "A"
            }
          ],
          "thresholds": [],
          "timeFrom": null,
          "timeRegions": [],
          "timeShift": null,
          "title": "Altertlog last modified $dbinstance",
          "tooltip": {
            "shared": true,
            "sort": 2,
            "value_type": "individual"
          },
          "type": "graph",
          "xaxis": {
            "buckets": null,
            "mode": "time",
            "name": null,
            "show": true,
            "values": []
          },
          "yaxes": [
            {
              "format": "s",
              "label": null,
              "logBase": 1,
              "max": null,
              "min": "0",
              "show": true
            },
            {
              "format": "short",
              "label": null,
              "logBase": 1,
              "max": null,
              "min": null,
              "show": true
            }
          ],
          "yaxis": {
            "align": false,
            "alignLevel": null
          }
        }
      ],
      "title": "Oracle errors",
      "type": "row"
    }
  ],
  "refresh": "30s",
  "schemaVersion": 22,
  "style": "dark",
  "tags": [
    "Oracle"
  ],
  "templating": {
    "list": [
      {
        "allValue": null,
        "current": {
          "text": "ORA19C",
          "value": "ORA19C"
        },
        "datasource": "RANCHER_MONITORING",
        "definition": "",
        "hide": 0,
        "includeAll": false,
        "index": -1,
        "label": "Database",
        "multi": false,
        "name": "database",
        "options": [],
        "query": "oracledb_uptime",
        "refresh": 1,
        "regex": "/database=\"([^\\\"]+)\"/",
        "skipUrlSync": false,
        "sort": 1,
        "tagValuesQuery": "",
        "tags": [],
        "tagsQuery": "",
        "type": "query",
        "useTags": false
      },
      {
        "allFormat": "glob",
        "allValue": null,
        "current": {
          "selected": false,
          "text": "All",
          "value": "$__all"
        },
        "datasource": "RANCHER_MONITORING",
        "definition": "",
        "hide": 0,
        "includeAll": true,
        "index": -1,
        "label": "Instance",
        "multi": true,
        "multiFormat": "regex values",
        "name": "dbinstance",
        "options": [],
        "query": "oracledb_uptime{database=\"$database\"}",
        "refresh": 1,
        "refresh_on_load": false,
        "regex": "/.*dbinstance=\"([^\\\"]+)/",
        "skipUrlSync": false,
        "sort": 1,
        "tagValuesQuery": null,
        "tags": [],
        "tagsQuery": null,
        "type": "query",
        "useTags": false
      },
      {
        "allValue": null,
        "current": {
          "text": "134.122.126.188:9162",
          "value": "134.122.126.188:9162"
        },
        "datasource": "RANCHER_MONITORING",
        "definition": "label_values(oracledb_up, instance)",
        "hide": 0,
        "includeAll": false,
        "index": -1,
        "label": null,
        "multi": false,
        "name": "host",
        "options": [],
        "query": "label_values(oracledb_up, instance)",
        "refresh": 1,
        "regex": "/[:]/",
        "skipUrlSync": false,
        "sort": 0,
        "tagValuesQuery": "",
        "tags": [],
        "tagsQuery": "",
        "type": "query",
        "useTags": false
      }
    ]
  },
  "time": {
    "from": "now-15m",
    "to": "now"
  },
  "timepicker": {
    "collapse": false,
    "enable": true,
    "notice": false,
    "now": true,
    "refresh_intervals": [
      "10s",
      "30s",
      "1m",
      "5m",
      "15m",
      "30m",
      "1h",
      "2h",
      "1d"
    ],
    "status": "Stable",
    "time_options": [
      "5m",
      "15m",
      "1h",
      "6h",
      "12h",
      "24h",
      "2d",
      "7d",
      "30d"
    ],
    "type": "timepicker"
  },
  "timezone": "browser",
  "title": "Oracle DB",
  "uid": "UcyAKPDGk",
  "variables": {
    "list": []
  },
  "version": 1
}